sphinx_modern_pdf_style/__init__.py
sphinx_modern_pdf_style/config.py
sphinx_modern_pdf_style/replacements.yaml
sphinx_modern_pdf_style/assets/LICENCE.txt
sphinx_modern_pdf_style/assets/Ubuntu-B.ttf
sphinx_modern_pdf_style/assets/Ubuntu-R.ttf
sphinx_modern_pdf_style/assets/Ubuntu-RI.ttf
sphinx_modern_pdf_style/assets/UbuntuMono-B.ttf
sphinx_modern_pdf_style/assets/UbuntuMono-R.ttf
sphinx_modern_pdf_style/assets/UbuntuMono-RI.ttf
sphinx_modern_pdf_style/assets/footer-generic.pdf-temp
sphinx_modern_pdf_style/assets/front-page-generic.pdf-temp
sphinx_modern_pdf_style/assets/front-page-light.pdf-temp
sphinx_modern_pdf_style/assets/latex_elements_template.txt
sphinx_modern_pdf_style/assets/placeholder.png
sphinx_modern_pdf_style-0.0.0.dist-info/METADATA
sphinx_modern_pdf_style-0.0.0.dist-info/WHEEL
sphinx_modern_pdf_style-0.0.0.dist-info/top_level.txt
sphinx_modern_pdf_style-0.0.0.dist-info/RECORD
