Metadata-Version: 2.1
Name: sphinx-modern-pdf-style
Version: 0.0.0
Summary: A modern PDF configuration
Author-email: Michael Park <admin@technicalwriting.info>
Classifier: Framework :: Sphinx
Classifier: Development Status :: 4 - Beta
Classifier: Environment :: Web Environment
Classifier: Intended Audience :: Other Audience
Classifier: Programming Language :: Python :: 3
Classifier: Programming Language :: Python :: 3.10
Classifier: Programming Language :: Python :: 3.11
Classifier: Programming Language :: Python :: 3.12
Classifier: Operating System :: OS Independent
Classifier: Topic :: Documentation
Classifier: Topic :: Software Development :: Documentation
Requires-Python: >=3.10
Requires-Dist: sphinx <9.0,>=6.0
Requires-Dist: pyyaml
